Metadata-Version: 2.1
Name: vdk-data-source-git
Version: 0.1.1184833162
Summary: Read Git repository data source
Home-page: https://github.com/vmware/versatile-data-kit
Project-URL: Documentation, https://github.com/vmware/versatile-data-kit/tree/main/projects/vdk-plugins/vdk-data-source-git
Project-URL: Source Code, https://github.com/vmware/versatile-data-kit/tree/main/projects/vdk-plugins/vdk-data-source-git
Project-URL: Bug Tracker, https://github.com/vmware/versatile-data-kit/issues/new/choose
Classifier: Development Status :: 2 - Pre-Alpha
Classifier: License :: OSI Approved :: Apache Software License
Classifier: Programming Language :: Python :: 3.7
Classifier: Programming Language :: Python :: 3.8
Classifier: Programming Language :: Python :: 3.9
Classifier: Programming Language :: Python :: 3.10
Classifier: Programming Language :: Python :: 3.11
Requires-Dist: vdk-core
Requires-Dist: vdk-data-sources
Requires-Dist: pygments
Requires-Dist: dulwich
